<?xml version="1.0" encoding="UTF-8"?>
<!-- Updated: 2025-07-28T04:54:39-05:00 -->
<EligibilityResponse xmlns="http://x12.org/schemas/005010/270271" version="005010" transactionSet="271">
  <TransactionHeader>
    <HierarchicalStructureCode>0022</HierarchicalStructureCode>
    <TransactionSetPurposeCode>11</TransactionSetPurposeCode>
    <ReferenceIdentification>ELG0137747</ReferenceIdentification>
    <Date>2025-07-28</Date>
    <Time>09:15:00</Time>
  </TransactionHeader>
  <InformationSource>
    <EntityIdentifierCode>PR</EntityIdentifierCode>
    <EntityTypeQualifier>2</EntityTypeQualifier>
    <OrganizationName>United Healthcare</OrganizationName>
    <PayerIdentification>87726</PayerIdentification>
  </InformationSource>
  <InformationReceiver>
    <EntityIdentifierCode>1P</EntityIdentifierCode>
    <EntityTypeQualifier>2</EntityTypeQualifier>
    <OrganizationName>Memorial Healthcare Center</OrganizationName>
    <ProviderIdentification>1234567890</ProviderIdentification>
  </InformationReceiver>
  <Subscriber>
    <EntityIdentifierCode>IL</EntityIdentifierCode>
    <EntityTypeQualifier>1</EntityTypeQualifier>
    <LastName>Anderson</LastName>
    <FirstName>Matthew</FirstName>
    <MiddleName></MiddleName>
    <MemberIdentification>KAI923456789</MemberIdentification>
    <SocialSecurityNumber>835-35-8505</SocialSecurityNumber>
    <DateOfBirth>1987-03-19</DateOfBirth>
    <Gender>M</Gender>
    <Address>
      <AddressLine>123 Main St</AddressLine>
      <City>Las Vegas</City>
      <State>NV</State>
      <PostalCode>89101</PostalCode>
    </Address>
  </Subscriber>
  <EligibilityInfo>
    <EligibilityCode>1</EligibilityCode>
    <PlanType>PPO</PlanType>
    <CoverageLevelCode>EMP</CoverageLevelCode>
    <ServiceTypeCode>30</ServiceTypeCode>
    <PlanCoverageDescription>PPO Standard Plan</PlanCoverageDescription>
    <EffectiveDate>2025-02-07</EffectiveDate>
    <TerminationDate></TerminationDate>
  </EligibilityInfo>
  <BenefitInfo>
    <CoverageLevel>IND</CoverageLevel>
    <ServiceTypeCode>30</ServiceTypeCode>
    <BenefitType>ActiveCoverage</BenefitType>
    <DeductibleAmount>1500.00</DeductibleAmount>
    <CopayAmount>25.00</CopayAmount>
    <CoInsurancePercent>80</CoInsurancePercent>
    <NetworkIndicator>Y</NetworkIndicator>
  </BenefitInfo>
</EligibilityResponse>